idesign_api_client/__init__.py
idesign_api_client/client.py
idesign_api_client/config.py
idesign_api_client/resources.py
idesign_api_client/utils.py
idesign_api_client-0.0.4.dist-info/METADATA
idesign_api_client-0.0.4.dist-info/WHEEL
idesign_api_client-0.0.4.dist-info/top_level.txt
idesign_api_client-0.0.4.dist-info/RECORD
